collection/__init__.py
collection/list.py
collection/queue.py
collection/stack.py
collection/vector.py
collection_plus-0.0.6.dist-info/DESCRIPTION.rst
collection_plus-0.0.6.dist-info/METADATA
collection_plus-0.0.6.dist-info/RECORD
collection_plus-0.0.6.dist-info/WHEEL
collection_plus-0.0.6.dist-info/metadata.json
collection_plus-0.0.6.dist-info/top_level.txt
