Metadata-Version: 2.0
Name: collection-plus
Version: 0.0.6
Summary: Collection utils
Home-page: https://github.com/bruca/collections
Author: Bruca Lock
Author-email: lockshi@hotmail.com
License: UNKNOWN
Keywords: collection collections
Platform: UNKNOWN
Classifier: Development Status :: 3 - Alpha
Classifier: Intended Audience :: Developers
Classifier: License :: OSI Approved :: MIT License
Classifier: Programming Language :: Python :: 2.7
Classifier: Programming Language :: Python :: 3
Classifier: Programming Language :: Python :: 3.4
Classifier: Programming Language :: Python :: 3.5
Classifier: Programming Language :: Python :: 3.6
